Workbook
Name NativeTimeline_Order_Date: #N/A
Name Slicer_Category: #N/A
Name Slicer_City: #N/A
Name Slicer_Payment_Method: #N/A
Name Slicer_Segment: #N/A

Sheet Raw_Data
A1: Order ID | B1: Order Date | C1: Ship Date | D1: Customer ID | E1: Customer Name | F1: Segment | G1: City | H1: Product ID | I1: Quantity | J1: Discount | K1: Ship Mode | L1: Payment Method | M1: Customer Age | N1: Rating
A2: ORD-102651 | B2: 28/03/2023 | C2: 2023-03-29 | D2: C2063 | E2: Tara Iyer | F2: Home Office | G2: Bengaluru | H2: P1014 | I2: 2 | J2: 0 | K2: Express | L2: UPI | M2: 25 | N2: 5
A3: ORD-102670 | B3: 2024-02-28 | C3: 2024-03-04 | D3: C2059 | E3: Arjun Singh | F3: Consumer | G3: Mumbai | H3: P1009 | I3: 3 | J3: 0.05 | K3: Standard | L3: Net Banking | M3: 18
A4: ORD-102774 | B4: 2023-04-03 | C4: 2023-04-10 | D4: C1821 | E4: Ishaan Khan | F4: Corporate | G4: Chennai | H4: P1009 | I4: 3 | J4: 0 | K4: Express | L4: Credit Card | M4: 27 | N4: 4
A5: ORD-101699 | B5: 2023-10-03 | C5: 06-Oct-2023 | D5: C1908 | E5: Kabir Nair | F5: Corporate | G5: Jaipur | H5: P1004 | I5: 6 | J5: 0 | K5: Standard | L5: Cash | M5: 46 | N5: 2
A6: ORD-101933 | B6: 2024-03-30 | C6: 2024-04-02 | D6: C2156 | E6: Meera Gupta | F6: Consumer | G6: Mumbai | H6: P1015 | I6: 1 | J6: 0 | K6: Express | L6: UPI | M6: 32 | N6: 1
A7: ORD-101368 | B7: 2024-04-08 | C7: 2024-04-13 | D7: C1083 | E7: Kabir Joshi | F7: Home Office | G7: Hyderabad | H7: P1016 | I7: 6 | J7: 0.15 | K7: Standard | L7: Net Banking | M7: 63 | N7: 4
A8: ORD-101317 | B8: 2023-01-13 | C8: 2023-01-19 | D8: C1257 | E8: Aarav Das | F8: Consumer | G8: Chennai | H8: P1018 | I8: 8 | J8: 0 | K8: Same Day | L8: UPI | M8: 60 | N8: 2
A9: ORD-102427 | B9: 05/11/2023 | C9: 2023-11-07 | D9: C1016 | E9: Zoya Reddy | F9: Corporate | G9: Mumbai | H9: P1003 | I9: 4 | J9: 0.15 | K9: Standard | L9: Credit Card | M9: 59 | N9: 5
A10: ORD-101559 | B10: 09/03/2024 | C10: 2024-03-13 | D10: C2033 | E10: Dev Khan | F10: home office | G10: Chennai | H10: P1010 | I10: 9 | J10: 0 | K10: Express | L10: Net Banking | M10: 52 | N10: 4
A11: ORD-101266 | B11: 2024-10-20 | C11: 2024-10-27 | D11: C2041 | E11: Ishaan Singh | F11: Home Office | G11: Kolkata | H11: P1002 | I11: 3 | J11: 0 | K11: Express | L11: UPI | M11: 42 | N11: 2
A12: ORD-102257 | B12: 2023-03-12 | C12: 2023-03-18 | D12: C1065 | E12: Aarav Sharma | F12: Home Office | G12: Bhubaneswar | H12: P1008 | I12: 6 | K12: Express | L12: Cash | M12: 52 | N12: 3
A13: ORD-100602 | B13: 2023-12-24 | C13: 2023-12-26 | D13: C1155 | E13: Dev Das | F13: Consumer | G13: Bengaluru | H13: P1016 | I13: 7 | J13: 0.1 | K13: Standard | L13: Cash | M13: 43 | N13: 3
A14: ORD-102261 | B14: 2024-01-25 | C14: 2024-01-26 | D14: C1888 | E14: Rahul Khan | F14: Corporate | G14: Chennai | H14: P1007 | I14: 7 | J14: 0 | K14: Standard | L14: Cash | M14: 32 | N14: 5
A15: ORD-101832 | B15: 2023-10-08 | C15: 2023-10-09 | D15: C1693 | E15: Arjun Das | F15: Corporate | G15: Ahmedabad | H15: P1016 | I15: 9 | J15: 0.1 | K15: Standard | L15: Credit Card | M15: 36 | N15: 5
A16: ORD-100347 | B16: 2024-09-30 | C16: 05-Oct-2024 | D16: C1562 | E16: Aarav Khan | F16: Corporate | G16: Ahmedabad | H16: P1003 | I16: 1 | J16: 0.2 | K16: Standard | L16: UPI | M16: 33 | N16: 4
A17: ORD-101406 | B17: 2024-02-22 | C17: 2024-02-23 | D17: C1412 | E17: Arjun Sharma | F17: Corporate | G17: Ahmedabad | H17: P1003 | I17: 1 | J17: 0.05 | L17: Cash | M17: 20 | N17: 2
A18: ORD-102431 | B18: 2023-04-09 | C18: 2023-04-16 | D18: C1297 | E18: DEV KHAN | F18: corporate | G18: Bengaluru | H18: P1016 | I18: 7 | J18: 0.15 | K18: Same Day | L18: UPI | M18: 29 | N18: 2
A19: ORD-100194 | B19: 11/03/2023 | C19: 2023-03-18 | D19: C2075 | E19: Kabir Gupta | F19: Consumer | G19: Hyderabad | H19: P1008 | I19: 2 | J19: 0.05 | K19: Standard | L19: UPI | M19: 35 | N19: 2
A20: ORD-100791 | B20: 2024-10-26 | C20: 31-Oct-2024 | D20: C1925 | E20: Ishaan Das | F20: Consumer | G20: Chennai | H20: P1007 | I20: 4 | J20: 0 | K20: Standard | L20: UPI | M20: 59 | N20: 3
A21: ORD-101858 | B21: 2023-08-05 | C21: 2023-08-12 | D21: C2026 | E21: Kabir Khan | F21: Home Office | G21: Kolkata | H21: P1012 | I21: 1 | J21: 0 | K21: Standard | L21: Credit Card | M21: 57 | N21: 4
A22: ORD-100795 | B22: 27/01/2023 | C22: 2023-02-03 | D22: C1062 | E22: Kabir Iyer | F22: consumer | G22: Ahmedabad | H22: P1011 | I22: 5 | J22: 0.1 | K22: Express | L22: Cash | M22: 64 | N22: 5
A23: ORD-102771 | B23: 2024-05-31 | C23: 2024-06-01 | D23: C1883 | E23: Zoya Gupta | F23: Home Office | G23: Bengaluru | H23: P1001 | I23: 1 | J23: 0.05 | K23: Standard | L23: Credit Card | M23: 60 | N23: 1
A24: ORD-100047 | B24: 2023-07-30 | C24: 2023-08-06 | D24: C2140 | E24: Rahul Das | F24: Corporate | G24: Hyderabad | H24: P1016 | I24: 8 | J24: 0.2 | K24: Standard | L24: Cash | M24: 22 | N24: 3
A25: ORD-100170 | B25: 2023-11-23 | C25: 2023-11-30 | D25: C1644 | E25: Diya Joshi | F25: Home Office | G25: Jaipur | H25: P1009 | I25: 2 | J25: 0.15 | K25: Same Day | L25: Net Banking | M25: 40 | N25: 4
A26: ORD-102533 | B26: 2023-12-04 | C26: 2023-12-08 | D26: C1204 | E26: RAHUL NAIR | F26: consumer | G26: Delhi | H26: P1005 | I26: 9 | J26: 0.05 | K26: Standard | L26: Credit Card | M26: 66 | N26: 4
A27: ORD-101474 | B27: 2023-05-20 | C27: 2023-05-27 | D27: C1503 | E27: Tara Iyer | F27: home office | G27: Bengaluru | H27: P1011 | I27: 3 | K27: Standard | L27: Net Banking | M27: 56 | N27: 4
A28: ORD-101316 | B28: 2024-02-10 | C28: 2024-02-12 | D28: C1463 | E28: Diya Gupta | F28: Consumer | G28: Bengaluru | H28: P1003 | I28: 6 | J28: 0 | K28: Express | L28: Net Banking | M28: 30 | N28: 2
A29: ORD-102523 | B29: 2024-11-11 | C29: 2024-11-14 | D29: C2107 | E29: Priya Sharma | F29: Home Office | G29: Patna | H29: P1004 | I29: 9 | J29: 0.15 | K29: Express | L29: UPI | M29: 67 | N29: 4
A30: ORD-101270 | B30: 24/11/2023 | C30: 2023-11-26 | D30: C1798 | E30: Zoya Singh | F30: Corporate | G30: Ahmedabad | H30: P1012 | I30: 6 | J30: 0.1 | L30: Net Banking | M30: 42 | N30: 4
A31: ORD-102769 | B31: 2024-09-25 | C31: 2024-09-26 | D31: C1279 | E31: Ishaan Reddy | F31: corporate | G31: Mumbai | H31: P1002 | I31: 5 | J31: 0 | K31: Standard | L31: Credit Card | M31: 36 | N31: 3
A32: ORD-101732 | B32: 2023-02-04 | C32: 11-Feb-2023 | D32: C1024 | E32: Priya Sharma | F32: Consumer | G32: Mumbai | H32: P1010 | I32: 7 | J32: 0.1 | K32: Standard | L32: Net Banking | M32: 69
A33: ORD-100890 | B33: 2023-12-04 | C33: 2023-12-09 | D33: C1658 | E33: ISHAAN VERMA | F33: Corporate | G33: Bhubaneswar | H33: P1007 | I33: 5 | J33: 0 | K33: Express | L33: Credit Card | M33: 28 | N33: 2
A34: ORD-101388 | B34: 2023-11-08 | C34: 2023-11-10 | D34: C1325 | E34: Meera Singh | F34: Consumer | G34: Ahmedabad | H34: P1006 | I34: 5 | J34: 0.1 | K34: Standard | L34: Cash | M34: 58 | N34: 2
A35: ORD-100463 | B35: 2024-06-28 | C35: 30-Jun-2024 | D35: C2117 | E35: Priya Reddy | F35: Corporate | G35: Kolkata | H35: P1016 | I35: 1 | J35: 0.1 | K35: Economy | L35: Credit Card | M35: 33 | N35: 4
A36: ORD-101762 | B36: 2023-06-28 | C36: 2023-06-29 | D36: C2074 | E36: Tara Sharma | F36: home office | G36: Delhi | H36: P1004 | I36: 7 | J36: 0 | K36: Economy | L36: Cash | M36: 65 | N36: 3
A37: ORD-102404 | B37: 2023-03-11 | C37: 2023-03-15 | D37: C1583 | E37: Sana Verma | F37: Consumer | G37: Bengaluru | H37: P1016 | I37: 2 | J37: 0.2 | K37: Economy | L37: Cash | M37: 37 | N37: 5
A38: ORD-101352 | B38: 2024-09-15 | C38: 2024-09-18 | D38: C2019 | E38: SANA REDDY | F38: Consumer | G38: Hyderabad | H38: P1015 | I38: 9 | J38: 0 | K38: Standard | L38: Credit Card | M38: 61 | N38: 4
A39: ORD-101059 | B39: 2024-10-24 | C39: 2024-10-26 | D39: C1761 | E39: Sana Verma | F39: Consumer | G39: Delhi | H39: P1013 | I39: 2 | J39: 0.05 | K39: Standard | L39: UPI | M39: 69 | N39: 1
A40: ORD-101831 | B40: 15/03/2023 | C40: 2023-03-16 | D40: C1823 | E40: Aarav Singh | F40: Corporate | G40: Patna | H40: P1018 | I40: 6 | J40: 0.2 | K40: Economy | L40: Cash | M40: 20 | N40: 2
A41: ORD-101128 | B41: 2023-08-20 | C41: 2023-08-22 | D41: C1138 | E41: Zoya Gupta | F41: Corporate | G41: Pune | H41: P1015 | I41: 5 | J41: 0.15 | K41: Standard | L41: Net Banking | M41: 29 | N41: 1
A42: ORD-100278 | B42: 22/06/2023 | C42: 2023-06-29 | D42: C1915 | E42: Meera Nair | F42: Consumer | G42: Ahmedabad | H42: P1011 | I42: 8 | J42: 0 | K42: Express | L42: Credit Card | M42: 66 | N42: 5
A43: ORD-101583 | B43: 2024-10-17 | C43: 2024-10-23 | D43: C2154 | E43: MEERA JOSHI | F43: Consumer | G43: Kolkata | H43: P1015 | I43: 6 | J43: 0.1 | K43: Express | L43: UPI | M43: 58 | N43: 1
A44: ORD-100000 | B44: 2024-05-09 | C44: 2024-05-16 | D44: C1977 | E44: Meera Khan | F44: Consumer | G44: Jaipur | H44: P1006 | I44: 5 | J44: 0.1 | K44: Standard | L44: Net Banking | M44: 65 | N44: 1
A45: ORD-100331 | B45: 2023-07-11 | C45: 2023-07-15 | D45: C1267 | E45: TARA REDDY | F45: Consumer | G45: Bengaluru | H45: P1001 | I45: 6 | J45: 0.2 | K45: Standard | L45: UPI | M45: 43 | N45: 2
A46: ORD-101398 | B46: 2024-11-15 | C46: 2024-11-22 | D46: C1176 | E46: Priya Joshi | F46: Home Office | G46: Pune | H46: P1012 | I46: 8 | J46: 0 | K46: Express | L46: UPI | M46: 68 | N46: 4
A47: ORD-100413 | B47: 2023-04-13 | C47: 2023-04-20 | D47: C1031 | E47: Dev Gupta | F47: Consumer | G47: Chennai | H47: P1002 | I47: 1 | J47: 0.2 | K47: Standard | L47: Credit Card | N47: 5
A48: ORD-101190 | B48: 2023-08-06 | C48: 2023-08-10 | D48: C1138 | E48: Zoya Gupta | F48: consumer | G48: Jaipur | H48: P1016 | I48: 8 | J48: 0 | K48: Express | L48: Cash | M48: 57 | N48: 1
A49: ORD-102805 | B49: 2023-03-07 | C49: 2023-03-12 | D49: C1584 | E49: PRIYA KHAN | F49: Corporate | G49: Bengaluru | H49: P1007 | I49: 3 | J49: 0.1 | K49: Same Day | L49: UPI | M49: 18 | N49: 3
A50: ORD-102282 | B50: 2023-02-17 | C50: 2023-02-21 | D50: C1183 | E50: Kabir Verma | F50: Consumer | G50: Chandigarh | H50: P1003 | I50: 3 | J50: 0.05 | K50: Standard | L50: Cash | M50: 37 | N50: 1
A51: ORD-100720 | B51: 13/04/2023 | C51: 2023-04-19 | D51: C1895 | E51: Zoya Joshi | F51: Corporate | G51: Ahmedabad | H51: P1004 | I51: 3 | K51: Express | L51: Cash | M51: 46 | N51: 2
A52: ORD-101108 | B52: 2023-03-29 | C52: 2023-03-31 | D52: C1864 | E52: Priya Verma | F52: Home Office | G52: Patna | H52: P1003 | I52: 5 | J52: 0 | K52: Standard | L52: Credit Card | M52: 52 | N52: 3
A53: ORD-100163 | B53: 2024-06-07 | C53: 2024-06-11 | D53: C1106 | E53: MEERA DAS | F53: Consumer | G53: Bengaluru | H53: P1017 | I53: 3 | J53: 0 | K53: Standard | L53: Cash | M53: 28 | N53: 1
A54: ORD-101039 | B54: 2024-12-23 | C54: 2024-12-26 | D54: C1693 | E54: Diya Singh | F54: Corporate | G54: Jaipur | H54: P1002 | I54: 2 | J54: 0.2 | K54: Express | L54: Credit Card | M54: 22 | N54: 5
A55: ORD-100430 | B55: 2024-04-29 | C55: 2024-05-03 | D55: C1213 | E55: AARAV SHARMA | F55: Consumer | G55: Jaipur | H55: P1011 | I55: 4 | J55: 0 | K55: Standard | L55: UPI | M55: 52 | N55: 5
A56: ORD-101949 | B56: 2024-12-26 | C56: 2025-01-02 | D56: C1273 | E56: Priya Nair | F56: Consumer | G56: Hyderabad | H56: P1012 | I56: 4 | J56: 0 | K56: Standard | L56: Net Banking | M56: 35 | N56: 1
A57: ORD-101071 | B57: 2023-12-27 | C57: 2024-01-01 | D57: C1371 | E57: Sana Joshi | F57: Consumer | G57: Kolkata | H57: P1005 | I57: 6 | J57: 0.05 | K57: Express | L57: UPI | M57: 47 | N57: 4
A58: ORD-100626 | B58: 2024-03-29 | C58: 30-Mar-2024 | D58: C1804 | E58: Kabir Khan | F58: consumer | G58: Bengaluru | H58: P1001 | I58: 1 | J58: 0.05 | K58: Standard | L58: Net Banking | M58: 24 | N58: 3
A59: ORD-101711 | B59: 2024-02-29 | C59: 2024-03-04 | D59: C2185 | E59: Arjun Joshi | F59: Consumer | G59: Ahmedabad | H59: P1009 | I59: 4 | J59: 0.2 | K59: Standard | L59: Net Banking | M59: 37
A60: ORD-101528 | B60: 2024-02-05 | C60: 12-Feb-2024 | D60: C1248 | E60: Kabir Verma | F60: Home Office | G60: Bhubaneswar | H60: P1007 | I60: 1 | J60: 0.1 | K60: Express | L60: Cash | M60: 28 | N60: 5
A61: ORD-101550 | B61: 2024-09-09 | C61: 2024-09-14 | D61: C1145 | E61: Dev Gupta | F61: Corporate | G61: Pune | H61: P1010 | I61: 6 | J61: 0.1 | K61: Standard | L61: UPI | M61: 30
A62: ORD-102571 | B62: 2024-11-21 | C62: 23-Nov-2024 | D62: C1350 | E62: Rahul Joshi | F62: Consumer | G62: Delhi | H62: P1016 | I62: 7 | J62: 0.1 | K62: Standard | L62: Credit Card | M62: 24 | N62: 1
A63: ORD-100874 | B63: 2023-11-22 | C63: 2023-11-28 | D63: C1298 | E63: ZOYA IYER | F63: Corporate | G63: Mumbai | H63: P1018 | I63: 9 | J63: 0.05 | K63: Express | L63: UPI | M63: 40 | N63: 1
A64: ORD-100281 | B64: 2024-02-10 | C64: 13-Feb-2024 | D64: C1376 | E64: Zoya Sharma | F64: Consumer | G64: Jaipur | H64: P1005 | I64: 6 | J64: 0.1 | K64: Standard | L64: Cash | M64: 23 | N64: 5
A65: ORD-102370 | B65: 2023-07-30 | C65: 2023-08-06 | D65: C1155 | E65: Priya Iyer | F65: Consumer | G65: Jaipur | H65: P1011 | I65: 8 | J65: 0.05 | K65: Economy | L65: UPI | M65: 67 | N65: 1
A66: ORD-101650 | B66: 2023-09-20 | C66: 2023-09-25 | D66: C1979 | E66: Rahul Iyer | F66: Consumer | G66: Chennai | H66: P1013 | I66: 3 | J66: 0 | K66: Standard | L66: Cash | M66: 58
A67: ORD-102347 | B67: 2024-04-23 | C67: 2024-04-30 | D67: C1151 | E67: Kabir Reddy | F67: Consumer | G67: Jaipur | H67: P1006 | I67: 5 | J67: 0.1 | K67: Same Day | L67: UPI | M67: 25 | N67: 3
A68: ORD-100325 | B68: 2023-09-30 | C68: 2023-10-01 | D68: C1567 | E68: Arjun Singh | F68: Consumer | H68: P1012 | I68: 1 | J68: 0 | K68: Standard | L68: Cash | N68: 1
A69: ORD-101532 | B69: 2023-08-05 | C69: 2023-08-06 | D69: C1654 | E69: Diya Singh | F69: Home Office | G69: Chandigarh | H69: P1005 | I69: 3 | J69: 0 | K69: Standard | L69: Credit Card | M69: 55 | N69: 5
A70: ORD-101340 | B70: 2024-10-12 | C70: 2024-10-15 | D70: C1873 | E70: Meera Khan | F70: Corporate | G70: Delhi | H70: P1006 | I70: 3 | J70: 0.05 | K70: Economy | L70: Cash | M70: 25 | N70: 5
A71: ORD-102155 | B71: 2023-09-03 | C71: 05-Sep-2023 | D71: C1021 | E71: Aarav Khan | F71: Consumer | G71: Hyderabad | H71: P1007 | I71: 9 | J71: 0 | K71: Standard | L71: Net Banking | M71: 48 | N71: 1
A72: ORD-101879 | B72: 02/04/2023 | C72: 2023-04-04 | D72: C1342 | E72: Dev Das | F72: Corporate | G72: Pune | H72: P1013 | I72: 2 | J72: 0.1 | K72: Standard | L72: Net Banking | M72: 55 | N72: 3
A73: ORD-100855 | B73: 2024-10-07 | C73: 2024-10-13 | D73: C1078 | E73: Priya Verma | F73: Consumer | G73: Mumbai | H73: P1001 | I73: 7 | J73: 0.2 | K73: Express | L73: Cash | M73: 32 | N73: 1
A74: ORD-101183 | B74: 2024-06-19 | C74: 2024-06-21 | D74: C1133 | E74: Arjun Khan | F74: corporate | G74: Hyderabad | H74: P1009 | I74: 2 | J74: 0.1 | K74: Express | L74: Net Banking | M74: 55 | N74: 5
A75: ORD-100668 | B75: 2024-01-13 | C75: 19-Jan-2024 | D75: C1634 | E75: SANA VERMA | F75: Consumer | G75: Bengaluru | H75: P1014 | I75: 5 | J75: 0 | K75: Express | L75: Cash | M75: 68
A76: ORD-102364 | B76: 2024-11-10 | C76: 2024-11-13 | D76: C1421 | E76: Priya Singh | F76: home office | G76: Bengaluru | H76: P1016 | I76: 3 | J76: 0.1 | K76: Standard | L76: Net Banking | M76: 66 | N76: 1
A77: ORD-102583 | B77: 11/05/2024 | C77: 2024-05-15 | D77: C1815 | E77: Diya Das | F77: Consumer | G77: Mumbai | H77: P1008 | I77: 5 | J77: 0 | K77: Express | L77: UPI | M77: 44 | N77: 1
A78: ORD-100953 | B78: 2024-06-21 | C78: 2024-06-23 | D78: C1931 | E78: Sana Khan | F78: Consumer | G78: Jaipur | H78: P1014 | I78: 8 | J78: 0.05 | K78: Standard | L78: Net Banking | M78: 45 | N78: 2
A79: ORD-102425 | B79: 2023-06-01 | C79: 2023-06-02 | D79: C1418 | E79: Kabir Iyer | F79: Consumer | G79: Hyderabad | H79: P1013 | I79: 7 | J79: 0.05 | K79: Same Day | L79: Cash | M79: 21 | N79: 4
A80: ORD-102021 | B80: 2023-11-03 | C80: 06-Nov-2023 | D80: C1782 | E80: Dev Verma | F80: Consumer | G80: Bengaluru | H80: P1015 | I80: 6 | J80: 0.05 | K80: Express | L80: Credit Card | M80: 53 | N80: 1
A81: ORD-100146 | B81: 2024-12-01 | C81: 2024-12-03 | D81: C1624 | E81: Aarav Sharma | F81: Home Office | G81: Kolkata | H81: P1016 | I81: 6 | J81: 0 | K81: Standard | L81: Credit Card | M81: 26 | N81: 1
A82: ORD-100424 | B82: 2023-11-12 | C82: 2023-11-13 | D82: C1435 | E82: Ishaan Verma | F82: Corporate | G82: Chandigarh | H82: P1006 | I82: 7 | K82: Standard | L82: Net Banking | M82: 23 | N82: 4
A83: ORD-100894 | B83: 2024-10-29 | C83: 05-Nov-2024 | D83: C1236 | E83: TARA IYER | F83: consumer | G83: Kolkata | H83: P1005 | I83: 9 | J83: 0 | K83: Standard | L83: Cash | M83: 37 | N83: 5
A84: ORD-102222 | B84: 2023-08-22 | C84: 2023-08-25 | D84: C2125 | E84: Kabir Das | F84: Consumer | G84: Chandigarh | H84: P1005 | I84: 1 | J84: 0.05 | K84: Express | L84: UPI | M84: 51 | N84: 1
A85: ORD-101748 | B85: 2024-12-13 | C85: 2024-12-15 | D85: C1532 | E85: MEERA JOSHI | F85: Consumer | G85: Kolkata | H85: P1003 | I85: 5 | J85: 0.15 | K85: Express | L85: Cash | M85: 69 | N85: 4
A86: ORD-101496 | B86: 2023-06-18 | C86: 25-Jun-2023 | D86: C1160 | E86: Zoya Nair | F86: Corporate | G86: Chennai | H86: P1016 | I86: 3 | J86: 0.15 | K86: Economy | L86: Cash | M86: 37 | N86: 2
A87: ORD-102746 | B87: 2023-02-20 | C87: 2023-02-24 | D87: C2166 | E87: Rahul Gupta | F87: Home Office | G87: Hyderabad | H87: P1012 | I87: 8 | J87: 0.1 | K87: Same Day | L87: Credit Card | M87: 23 | N87: 5
A88: ORD-100406 | B88: 2024-03-11 | C88: 2024-03-16 | D88: C1511 | E88: Dev Khan | F88: Home Office | G88: Delhi | H88: P1006 | I88: 4 | J88: 0.05 | K88: Same Day | L88: Net Banking | M88: 29 | N88: 1
A89: ORD-102040 | B89: 2023-08-11 | C89: 2023-08-17 | D89: C1189 | E89: Diya Sharma | F89: Corporate | G89: Delhi | H89: P1016 | I89: 1 | J89: 0 | K89: Standard | L89: UPI | M89: 42 | N89: 2
A90: ORD-102857 | B90: 2024-09-22 | C90: 2024-09-27 | D90: C1071 | E90: Ishaan Iyer | F90: Home Office | G90: Bhubaneswar | H90: P1006 | I90: 6 | J90: 0 | K90: Standard | L90: Net Banking | M90: 69 | N90: 5
A91: ORD-100353 | B91: 2024-07-21 | C91: 2024-07-28 | D91: C1805 | E91: Priya Das | F91: Consumer | G91: Mumbai | H91: P1011 | I91: 1 | J91: 0 | K91: Standard | L91: Cash | M91: 67 | N91: 3
A92: ORD-101564 | B92: 2024-05-04 | C92: 2024-05-06 | D92: C1087 | E92: MEERA DAS | F92: home office | G92: Patna | H92: P1018 | I92: 7 | J92: 0 | K92: Same Day | L92: UPI | M92: 49 | N92: 2
A93: ORD-100621 | B93: 2023-04-07 | C93: 2023-04-08 | D93: C1371 | E93: Ishaan Gupta | F93: Consumer | G93: Bhubaneswar | H93: P1001 | I93: 9 | J93: 0 | K93: Standard | L93: Cash | M93: 65 | N93: 2
A94: ORD-100883 | B94: 25/05/2024 | C94: 2024-05-30 | D94: C2011 | E94: Rahul Singh | F94: Consumer | G94: Hyderabad | H94: P1012 | I94: 2 | J94: 0.15 | K94: Same Day | L94: Credit Card | M94: 57 | N94: 4
... A103: ORD-101422 | B103: 2024-10-17 | C103: 2024-10-21 | D103: C1751 | E103: Kabir Iyer | F103: Consumer | G103: Bhubaneswar | H103: P1016 | I103: 1 | J103: 0.1 | K103: Express | L103: Credit Card | M103: 40 | N103: 5
A104: ORD-101837 | B104: 2023-05-12 | C104: 16-May-2023 | D104: C2158 | E104: RAHUL SINGH | F104: Consumer | G104: Chandigarh | H104: P1007 | I104: 9 | K104: Standard | L104: Cash | M104: 18
A105: ORD-101064 | B105: 2023-05-21 | C105: 2023-05-27 | D105: C1806 | E105: Kabir Iyer | F105: Consumer | G105: Chandigarh | H105: P1018 | I105: 1 | J105: 0 | K105: Standard | L105: Net Banking | M105: 32 | N105: 3
A106: ORD-101757 | B106: 2023-02-02 | C106: 2023-02-08 | D106: C1181 | E106: Diya Singh | F106: home office | G106: Patna | H106: P1006 | I106: 2 | J106: 0.05 | K106: Same Day | L106: Net Banking | M106: 64 | N106: 3
A107: ORD-100426 | B107: 2024-04-08 | C107: 2024-04-10 | D107: C1162 | E107: Meera Singh | F107: Home Office | G107: Ahmedabad | H107: P1006 | I107: 9 | J107: 0.15 | K107: Express | L107: Cash | M107: 61 | N107: 3
A108: ORD-100838 | B108: 2023-02-08 | C108: 2023-02-14 | D108: C1876 | E108: Ishaan Reddy | F108: Home Office | G108: Patna | H108: P1012 | I108: 5 | K108: Express | L108: UPI | N108: 4
...

Sheet Product_Master
A1: Product ID | B1: Product Name | C1: Category | D1: Unit Price | E1: Unit Cost
A2: P1001 | B2: Laptop | C2: Technology | D2: 900 | E2: 669.14
A3: P1002 | B3: Smartphone | C3: Technology | D3: 600 | E3: 395.83
A4: P1003 | B4: Tablet | C4: Technology | D4: 350 | E4: 267.63
A5: P1004 | B5: Monitor | C5: Technology | D5: 220 | E5: 159.36
A6: P1005 | B6: Headphones | C6: Technology | D6: 80 | E6: 45.88
A7: P1006 | B7: Keyboard | C7: Technology | D7: 45 | E7: 35.73
A8: P1007 | B8: Printer | C8: Technology | D8: 180 | E8: 133.25
A9: P1008 | B9: Office Chair | C9: Furniture | D9: 150 | E9: 111.98
A10: P1009 | B10: Desk | C10: Furniture | D10: 320 | E10: 186.25
A11: P1010 | B11: Bookcase | C11: Furniture | D11: 210 | E11: 139.15
A12: P1011 | B12: Filing Cabinet | C12: Furniture | D12: 130 | E12: 83.55
A13: P1012 | B13: Standing Desk | C13: Furniture | D13: 480 | E13: 375.21
... A19: P1018 | B19: Marker Pack | C19: Office Supplies | D19: 11 | E19: 6.23

Sheet Clean_Data
A1: Order ID | B1: Order Date | C1: Ship Date | D1: Customer ID | E1: Customer Name | F1: Segment | G1: City | H1: Product ID | I1: Quantity | J1: Discount | K1: Ship Mode | L1: Payment Method | M1: Customer Age | N1: Rating | O1: Product Name | P1: Category | Q1: Unit Price | R1: Unit Cost | S1: Sales | T1: Cost | U1: Profit | V1: Profit Margin | W1: Profit Status | X1: Sales Category
A2: ORD-102651 | B2: 45013 | C2: 45014 | D2: C2063 | E2: Tara Iyer | F2: Home Office | G2: Bengaluru | H2: P1014 | I2: 2 | J2: 0 | K2: Express | L2: UPI | M2: 25 | N2: 5 | O2: =VLOOKUP(H2,Product_Master!$A$2:$E$19,2,FALSE) -> Pen Set | P2: =VLOOKUP(H2,Product_Master!$A$2:$E$19,3,FALSE) -> Office Supplies | Q2: =INDEX(Product_Master!$D$2:$D$19,MATCH(H2,Product_Master!$A$2:$A$19,0)) -> 12 | R2: =INDEX(Product_Master!$E$2:$E$19,MATCH(H2,Product_Master!$A$2:$A$19,0)) -> 9.07 | S2: =I2*Q2*(1-J2) -> 24 | T2: =I2*R2 -> 18.14 | U2: =S2-T2 -> 5.86 | V2: =IFERROR(U2/S2,0) -> 0.24416667 | W2: =IF(U2>0,"Profitable","Loss") -> Profitable | X2: =IF(S2>=5000,"High",IF(S2>=2000,"Medium","Low")) -> Low
A3: ORD-102670 | B3: 45350 | C3: 45355 | D3: C2059 | E3: Arjun Singh | F3: Consumer | G3: Mumbai | H3: P1009 | I3: 3 | J3: 0.05 | K3: Standard | L3: Net Banking | M3: 18 | N3: 3 | O3: =VLOOKUP(H3,Product_Master!$A$2:$E$19,2,FALSE) -> Desk | P3: =VLOOKUP(H3,Product_Master!$A$2:$E$19,3,FALSE) -> Furniture | Q3: =INDEX(Product_Master!$D$2:$D$19,MATCH(H3,Product_Master!$A$2:$A$19,0)) -> 320 | R3: =INDEX(Product_Master!$E$2:$E$19,MATCH(H3,Product_Master!$A$2:$A$19,0)) -> 186.25 | S3: =I3*Q3*(1-J3) -> 912 | T3: =I3*R3 -> 558.75 | U3: =S3-T3 -> 353.25 | V3: =IFERROR(U3/S3,0) -> 0.38733553 | W3: =IF(U3>0,"Profitable","Loss") -> Profitable | X3: =IF(S3>=5000,"High",IF(S3>=2000,"Medium","Low")) -> Low
A4: ORD-102774 | B4: 45019 | C4: 45026 | D4: C1821 | E4: Ishaan Khan | F4: Corporate | G4: Chennai | H4: P1009 | I4: 3 | J4: 0 | K4: Express | L4: Credit Card | M4: 27 | N4: 4 | O4: =VLOOKUP(H4,Product_Master!$A$2:$E$19,2,FALSE) -> Desk | P4: =VLOOKUP(H4,Product_Master!$A$2:$E$19,3,FALSE) -> Furniture | Q4: =INDEX(Product_Master!$D$2:$D$19,MATCH(H4,Product_Master!$A$2:$A$19,0)) -> 320 | R4: =INDEX(Product_Master!$E$2:$E$19,MATCH(H4,Product_Master!$A$2:$A$19,0)) -> 186.25 | S4: =I4*Q4*(1-J4) -> 960 | T4: =I4*R4 -> 558.75 | U4: =S4-T4 -> 401.25 | V4: =IFERROR(U4/S4,0) -> 0.41796875 | W4: =IF(U4>0,"Profitable","Loss") -> Profitable | X4: =IF(S4>=5000,"High",IF(S4>=2000,"Medium","Low")) -> Low
A5: ORD-101699 | B5: 45202 | C5: 45205 | D5: C1908 | E5: Kabir Nair | F5: Corporate | G5: Jaipur | H5: P1004 | I5: 6 | J5: 0 | K5: Standard | L5: Cash | M5: 46 | N5: 2 | O5: =VLOOKUP(H5,Product_Master!$A$2:$E$19,2,FALSE) -> Monitor | P5: =VLOOKUP(H5,Product_Master!$A$2:$E$19,3,FALSE) -> Technology | Q5: =INDEX(Product_Master!$D$2:$D$19,MATCH(H5,Product_Master!$A$2:$A$19,0)) -> 220 | R5: =INDEX(Product_Master!$E$2:$E$19,MATCH(H5,Product_Master!$A$2:$A$19,0)) -> 159.36 | S5: =I5*Q5*(1-J5) -> 1320 | T5: =I5*R5 -> 956.16 | U5: =S5-T5 -> 363.84 | V5: =IFERROR(U5/S5,0) -> 0.27563636 | W5: =IF(U5>0,"Profitable","Loss") -> Profitable | X5: =IF(S5>=5000,"High",IF(S5>=2000,"Medium","Low")) -> Low
A6: ORD-101933 | B6: 45381 | C6: 45384 | D6: C2156 | E6: Meera Gupta | F6: Consumer | G6: Mumbai | H6: P1015 | I6: 1 | J6: 0 | K6: Express | L6: UPI | M6: 32 | N6: 1 | O6: =VLOOKUP(H6,Product_Master!$A$2:$E$19,2,FALSE) -> Stapler | P6: =VLOOKUP(H6,Product_Master!$A$2:$E$19,3,FALSE) -> Office Supplies | Q6: =INDEX(Product_Master!$D$2:$D$19,MATCH(H6,Product_Master!$A$2:$A$19,0)) -> 15 | R6: =INDEX(Product_Master!$E$2:$E$19,MATCH(H6,Product_Master!$A$2:$A$19,0)) -> 9.91 | S6: =I6*Q6*(1-J6) -> 15 | T6: =I6*R6 -> 9.91 | U6: =S6-T6 -> 5.09 | V6: =IFERROR(U6/S6,0) -> 0.33933333 | W6: =IF(U6>0,"Profitable","Loss") -> Profitable | X6: =IF(S6>=5000,"High",IF(S6>=2000,"Medium","Low")) -> Low
A7: ORD-101368 | B7: 45390 | C7: 45395 | D7: C1083 | E7: Kabir Joshi | F7: Home Office | G7: Hyderabad | H7: P1016 | I7: 6 | J7: 0.15 | K7: Standard | L7: Net Banking | M7: 63 | N7: 4 | O7: =VLOOKUP(H7,Product_Master!$A$2:$E$19,2,FALSE) -> Paper Ream | P7: =VLOOKUP(H7,Product_Master!$A$2:$E$19,3,FALSE) -> Office Supplies | Q7: =INDEX(Product_Master!$D$2:$D$19,MATCH(H7,Product_Master!$A$2:$A$19,0)) -> 9 | R7: =INDEX(Product_Master!$E$2:$E$19,MATCH(H7,Product_Master!$A$2:$A$19,0)) -> 5.46 | S7: =I7*Q7*(1-J7) -> 45.9 | T7: =I7*R7 -> 32.76 | U7: =S7-T7 -> 13.14 | V7: =IFERROR(U7/S7,0) -> 0.28627451 | W7: =IF(U7>0,"Profitable","Loss") -> Profitable | X7: =IF(S7>=5000,"High",IF(S7>=2000,"Medium","Low")) -> Low
A8: ORD-101317 | B8: 44939 | C8: 44945 | D8: C1257 | E8: Aarav Das | F8: Consumer | G8: Chennai | H8: P1018 | I8: 8 | J8: 0 | K8: Same Day | L8: UPI | M8: 60 | N8: 2 | O8: =VLOOKUP(H8,Product_Master!$A$2:$E$19,2,FALSE) -> Marker Pack | P8: =VLOOKUP(H8,Product_Master!$A$2:$E$19,3,FALSE) -> Office Supplies | Q8: =INDEX(Product_Master!$D$2:$D$19,MATCH(H8,Product_Master!$A$2:$A$19,0)) -> 11 | R8: =INDEX(Product_Master!$E$2:$E$19,MATCH(H8,Product_Master!$A$2:$A$19,0)) -> 6.23 | S8: =I8*Q8*(1-J8) -> 88 | T8: =I8*R8 -> 49.84 | U8: =S8-T8 -> 38.16 | V8: =IFERROR(U8/S8,0) -> 0.43363636 | W8: =IF(U8>0,"Profitable","Loss") -> Profitable | X8: =IF(S8>=5000,"High",IF(S8>=2000,"Medium","Low")) -> Low
A9: ORD-102427 | B9: 45235 | C9: 45237 | D9: C1016 | E9: Zoya Reddy | F9: Corporate | G9: Mumbai | H9: P1003 | I9: 4 | J9: 0.15 | K9: Standard | L9: Credit Card | M9: 59 | N9: 5 | O9: =VLOOKUP(H9,Product_Master!$A$2:$E$19,2,FALSE) -> Tablet | P9: =VLOOKUP(H9,Product_Master!$A$2:$E$19,3,FALSE) -> Technology | Q9: =INDEX(Product_Master!$D$2:$D$19,MATCH(H9,Product_Master!$A$2:$A$19,0)) -> 350 | R9: =INDEX(Product_Master!$E$2:$E$19,MATCH(H9,Product_Master!$A$2:$A$19,0)) -> 267.63 | S9: =I9*Q9*(1-J9) -> 1190 | T9: =I9*R9 -> 1070.52 | U9: =S9-T9 -> 119.48 | V9: =IFERROR(U9/S9,0) -> 0.10040336 | W9: =IF(U9>0,"Profitable","Loss") -> Profitable | X9: =IF(S9>=5000,"High",IF(S9>=2000,"Medium","Low")) -> Low
A10: ORD-101559 | B10: 45360 | C10: 45364 | D10: C2033 | E10: Dev Khan | F10: Home Office | G10: Chennai | H10: P1010 | I10: 9 | J10: 0 | K10: Express | L10: Net Banking | M10: 52 | N10: 4 | O10: =VLOOKUP(H10,Product_Master!$A$2:$E$19,2,FALSE) -> Bookcase | P10: =VLOOKUP(H10,Product_Master!$A$2:$E$19,3,FALSE) -> Furniture | Q10: =INDEX(Product_Master!$D$2:$D$19,MATCH(H10,Product_Master!$A$2:$A$19,0)) -> 210 | R10: =INDEX(Product_Master!$E$2:$E$19,MATCH(H10,Product_Master!$A$2:$A$19,0)) -> 139.15 | S10: =I10*Q10*(1-J10) -> 1890 | T10: =I10*R10 -> 1252.35 | U10: =S10-T10 -> 637.65 | V10: =IFERROR(U10/S10,0) -> 0.33738095 | W10: =IF(U10>0,"Profitable","Loss") -> Profitable | X10: =IF(S10>=5000,"High",IF(S10>=2000,"Medium","Low")) -> Low
A11: ORD-101266 | B11: 45585 | C11: 45592 | D11: C2041 | E11: Ishaan Singh | F11: Home Office | G11: Kolkata | H11: P1002 | I11: 3 | J11: 0 | K11: Express | L11: UPI | M11: 42 | N11: 2 | O11: =VLOOKUP(H11,Product_Master!$A$2:$E$19,2,FALSE) -> Smartphone | P11: =VLOOKUP(H11,Product_Master!$A$2:$E$19,3,FALSE) -> Technology | Q11: =INDEX(Product_Master!$D$2:$D$19,MATCH(H11,Product_Master!$A$2:$A$19,0)) -> 600 | R11: =INDEX(Product_Master!$E$2:$E$19,MATCH(H11,Product_Master!$A$2:$A$19,0)) -> 395.83 | S11: =I11*Q11*(1-J11) -> 1800 | T11: =I11*R11 -> 1187.49 | U11: =S11-T11 -> 612.51 | V11: =IFERROR(U11/S11,0) -> 0.34028333 | W11: =IF(U11>0,"Profitable","Loss") -> Profitable | X11: =IF(S11>=5000,"High",IF(S11>=2000,"Medium","Low")) -> Low
A12: ORD-102257 | B12: 44997 | C12: 45003 | D12: C1065 | E12: Aarav Sharma | F12: Home Office | G12: Bhubaneswar | H12: P1008 | I12: 6 | J12: 0 | K12: Express | L12: Cash | M12: 52 | N12: 3 | O12: =VLOOKUP(H12,Product_Master!$A$2:$E$19,2,FALSE) -> Office Chair | P12: =VLOOKUP(H12,Product_Master!$A$2:$E$19,3,FALSE) -> Furniture | Q12: =INDEX(Product_Master!$D$2:$D$19,MATCH(H12,Product_Master!$A$2:$A$19,0)) -> 150 | R12: =INDEX(Product_Master!$E$2:$E$19,MATCH(H12,Product_Master!$A$2:$A$19,0)) -> 111.98 | S12: =I12*Q12*(1-J12) -> 900 | T12: =I12*R12 -> 671.88 | U12: =S12-T12 -> 228.12 | V12: =IFERROR(U12/S12,0) -> 0.25346667 | W12: =IF(U12>0,"Profitable","Loss") -> Profitable | X12: =IF(S12>=5000,"High",IF(S12>=2000,"Medium","Low")) -> Low
A13: ORD-100602 | B13: 45284 | C13: 45286 | D13: C1155 | E13: Dev Das | F13: Consumer | G13: Bengaluru | H13: P1016 | I13: 7 | J13: 0.1 | K13: Standard | L13: Cash | M13: 43 | N13: 3 | O13: =VLOOKUP(H13,Product_Master!$A$2:$E$19,2,FALSE) -> Paper Ream | P13: =VLOOKUP(H13,Product_Master!$A$2:$E$19,3,FALSE) -> Office Supplies | Q13: =INDEX(Product_Master!$D$2:$D$19,MATCH(H13,Product_Master!$A$2:$A$19,0)) -> 9 | R13: =INDEX(Product_Master!$E$2:$E$19,MATCH(H13,Product_Master!$A$2:$A$19,0)) -> 5.46 | S13: =I13*Q13*(1-J13) -> 56.7 | T13: =I13*R13 -> 38.22 | U13: =S13-T13 -> 18.48 | V13: =IFERROR(U13/S13,0) -> 0.32592593 | W13: =IF(U13>0,"Profitable","Loss") -> Profitable | X13: =IF(S13>=5000,"High",IF(S13>=2000,"Medium","Low")) -> Low
... A2881: ORD-102254 | B2881: 45343 | C2881: 45346 | D2881: C1375 | E2881: Zoya Nair | F2881: Consumer | G2881: Bhubaneswar | H2881: P1016 | I2881: 3 | J2881: 0 | K2881: Standard | L2881: Cash | M2881: 59 | N2881: 1 | O2881: =VLOOKUP(H2881,Product_Master!$A$2:$E$19,2,FALSE) -> Paper Ream | P2881: =VLOOKUP(H2881,Product_Master!$A$2:$E$19,3,FALSE) -> Office Supplies | Q2881: =INDEX(Product_Master!$D$2:$D$19,MATCH(H2881,Product_Master!$A$2:$A$19,0)) -> 9 | R2881: =INDEX(Product_Master!$E$2:$E$19,MATCH(H2881,Product_Master!$A$2:$A$19,0)) -> 5.46 | S2881: =I2881*Q2881*(1-J2881) -> 27 | T2881: =I2881*R2881 -> 16.38 | U2881: =S2881-T2881 -> 10.62 | V2881: =IFERROR(U2881/S2881,0) -> 0.39333333 | W2881: =IF(U2881>0,"Profitable","Loss") -> Profitable | X2881: =IF(S2881>=5000,"High",IF(S2881>=2000,"Medium","Low")) -> Low

Sheet Pivot_Tables
A1: Retail Sales Analysis – Pivot Tables
B3: 1. Sales by Category | E3: 4. Profit by Category | H3: 6. Monthly Sales
B4: Row Labels | C4: Sum of Sales | E4: Row Labels | F4: Sum of Profit | H4: Row Labels | I4: Sum of Sales
B5: Furniture | C5: 951387 | E5: Furniture | F5: 241829.13 | H5: Jan | I5: 228345.25
B6: Office Supplies | C6: 45595.5 | E6: Office Supplies | F6: 13430.93 | H6: Feb | I6: 219347.25
B7: Technology | C7: 1869001 | E7: Technology | F7: 418098.75 | H7: Mar | I7: 261648.9
B8: Grand Total | C8: 2865983.5 | E8: Grand Total | F8: 673358.81 | H8: Apr | I8: 254071.2
H9: May | I9: 259049.15
B10: 2. Sales by Customer Segment | E10: 5. Sales by City | H10: Jun | I10: 188602.9
B11: Row Labels | C11: Sum of Sales | E11: Row Labels | F11: Sum of Sales | H11: Jul | I11: 249937.4
B12: Consumer | C12: 1516400.9 | E12: Ahmedabad | F12: 258893.8 | H12: Aug | I12: 267365.4
B13: Corporate | C13: 815038.85 | E13: Bengaluru | F13: 252690.25 | H13: Sep | I13: 215363.5
B14: Home Office | C14: 534543.7 | E14: Chennai | F14: 258756.6 | H14: Oct | I14: 229998.1
B15: Grand Total | C15: 2865983.5 | E15: Jaipur | F15: 260841.65 | H15: Nov | I15: 239124.25
E16: Mumbai | F16: 263146 | H16: Dec | I16: 253130.2
B17: 3. Sales by Payment Method | E17: Grand Total | F17: 1294328.3 | H17: Grand Total | I17: 2865983.5
B18: Row Labels | C18: Sum of Sales
B19: Cash | C19: 767000.7
B20: Credit Card | C20: 664817.15
B21: Net Banking | C21: 739049.85
B22: UPI | C22: 695115.8
B23: Grand Total | C23: 2865983.5

Sheet Charts
A1: Retail Sales Analysis – Data Visualization

Sheet Dashboard
A1: 🛍️ RETAIL SALES ANALYTICS DASHBOARD 📊 Sales Performance • 💰 Profitability • 👥 Customer Insights
B3: 💰 Total Sales | G3: 📈 Total Profit | L3: 🛍️ Total Orders | Q3: 📦 Total Quantity Sold
B4: =SUM(Clean_Data!S2:S2881) -> 2865983.5 | G4: =SUM(Clean_Data!U2:U2881) -> 673358.81 | L4: =COUNTA(Clean_Data!A2:A2881) -> 2880 | Q4: =SUM(Clean_Data!I2:I2881) -> 14287
